MetricVis/__init__.py
MetricVis/actual_forecast.py
MetricVis/utils.py
MetricVis/week_month_trend.py
metric_vis-0.0.18.dist-info/METADATA
metric_vis-0.0.18.dist-info/WHEEL
metric_vis-0.0.18.dist-info/top_level.txt
metric_vis-0.0.18.dist-info/RECORD
